sabg/__init__.py
sabg/init_config.py
sabg/main.py
sabg/modules/__init__.py
sabg/modules/background.py
sabg/modules/io.py
sabg/modules/mask_utils.py
sabg/modules/metrics.py
sabg/modules/model.py
sabg/modules/pipeline.py
sabg_analysis-0.1.6.dist-info/METADATA
sabg_analysis-0.1.6.dist-info/WHEEL
sabg_analysis-0.1.6.dist-info/entry_points.txt
sabg_analysis-0.1.6.dist-info/top_level.txt
sabg_analysis-0.1.6.dist-info/RECORD
