Metadata-Version: 2.4
Name: sabg-analysis
Version: 0.1.6
Summary: Tool for quantitative digital in situ senescence-associated β-galactosidase assay analysis of fibroblasts
Author-email: Nikita <nikita.sedlyar@yandex.ru>
License: For academic/non-commercial use only.
Requires-Python: >=3.9
Requires-Dist: huggingface-hub==0.32.3
Requires-Dist: numpy==2.2.6
Requires-Dist: opencv-python==4.11.0.86
Requires-Dist: pandas==2.2.3
Requires-Dist: PyYAML==6.0.2
Requires-Dist: scikit-image==0.25.2
Requires-Dist: torch==2.7.0
Requires-Dist: torchvision==0.22.0
Requires-Dist: tqdm==4.67.1
Requires-Dist: openpyxl==3.1.5
